google_docstring_parser/__init__.py
google_docstring_parser/google_docstring_parser.py
google_docstring_parser/py.typed
google_docstring_parser/type_validation.py
google_docstring_parser-0.0.9.dist-info/licenses/LICENSE
tools/__init__.py
tools/check_docstrings.py
google_docstring_parser-0.0.9.dist-info/METADATA
google_docstring_parser-0.0.9.dist-info/WHEEL
google_docstring_parser-0.0.9.dist-info/top_level.txt
google_docstring_parser-0.0.9.dist-info/RECORD
