Metadata-Version: 2.4
Name: google-docstring-parser
Version: 0.0.9
Summary: A lightweight, efficient parser for Google-style Python docstrings that converts them into structured dictionaries.
Author: Vladimir Iglovikov
Maintainer: Vladimir Iglovikov
License: Custom License - See LICENSE file for details
Keywords: docstring,documentation,google-style,parser,python,static-analysis,type-hints
Classifier: Development Status :: 5 - Production/Stable
Classifier: Intended Audience :: Developers
Classifier: Intended Audience :: Science/Research
Classifier: License :: Other/Proprietary License
Classifier: Operating System :: OS Independent
Classifier: Programming Language :: Python
Classifier: Programming Language :: Python :: 3 :: Only
Classifier: Programming Language :: Python :: 3.10
Classifier: Programming Language :: Python :: 3.11
Classifier: Programming Language :: Python :: 3.12
Classifier: Programming Language :: Python :: 3.13
Classifier: Programming Language :: Python :: 3.14
Classifier: Topic :: Scientific/Engineering :: Artificial Intelligence
Classifier: Topic :: Software Development :: Documentation
Classifier: Topic :: Software Development :: Libraries
Classifier: Topic :: Software Development :: Libraries :: Python Modules
Classifier: Typing :: Typed
Requires-Python: >=3.10
License-File: LICENSE
Requires-Dist: docstring-parser>=0.16
Provides-Extra: dev
Requires-Dist: pre-commit>=3.5; extra == "dev"
Requires-Dist: pytest>=8.3.3; extra == "dev"
Dynamic: license-file
